Jati/ClientHandler.py
Jati/ErrorHandler.py
Jati/HTTPServerSan.py
Jati/SocketFileSVR.py
Jati/Websck.py
Jati/__init__.py
Jati/__main__.py
Jati/Base/App.py
Jati/Base/Auth.py
Jati/Base/Controller.py
Jati/Base/Log.py
Jati/Base/Route.py
Jati/Base/Service.py
Jati/Base/Session.py
Jati/Base/__init__.py
Jati/CLI/Generator.py
Jati/CLI/Serve.py
Jati/CLI/__init__.py
Jati/Database/__init__.py
Jati/Database/SQL/Connection.py
Jati/Database/SQL/Database.py
Jati/Database/SQL/Model.py
Jati/Database/SQL/Query.py
Jati/Database/SQL/__init__.py
Jati/Database/SQL/mysql/Connection.py
Jati/Database/SQL/mysql/Query.py
Jati/Database/SQL/mysql/__init__.py
Jati/Database/noSQL/Connection.py
Jati/Database/noSQL/Database.py
Jati/Database/noSQL/Model.py
Jati/Database/noSQL/Query.py
Jati/Database/noSQL/__init__.py
Jati/Database/noSQL/mongo/Connection.py
Jati/Database/noSQL/mongo/Query.py
Jati/Database/noSQL/mongo/__init__.py
Jati-0.0.2.dist-info/LICENSE
Jati-0.0.2.dist-info/METADATA
Jati-0.0.2.dist-info/WHEEL
Jati-0.0.2.dist-info/entry_points.txt
Jati-0.0.2.dist-info/top_level.txt
Jati-0.0.2.dist-info/RECORD
