Metadata-Version: 2.1
Name: Jati
Version: 0.0.2
Summary: Jati merupakan modul python untuk restAPI dan websocket
Home-page: https://github.com/ghuvrons/Jati
Author: Janoko
Author-email: janoko@sandhika.com
License: UNKNOWN
Platform: UNKNOWN
Classifier: Programming Language :: Python :: 3
Classifier: License :: OSI Approved :: MIT License
Classifier: Operating System :: OS Independent
Requires-Python: >=3.7
Requires-Dist: click (>=5.1)
Requires-Dist: PyMySQL (==1.0.2)
